django_urlconf_export/__init__.py
django_urlconf_export/export_urlconf.py
django_urlconf_export/import_urlconf.py
django_urlconf_export/language_utils.py
django_urlconf_export/urlconf_qa.py
django_urlconf_export/management/__init__.py
django_urlconf_export/management/commands/__init__.py
django_urlconf_export/management/commands/export_urlconf_to_file.py
django_urlconf_export/views/__init__.py
django_urlconf_export/views/export.py
django_urlconf_export/views/http404.py
django_urlconf_export-1.1.1.dist-info/METADATA
django_urlconf_export-1.1.1.dist-info/WHEEL
django_urlconf_export-1.1.1.dist-info/top_level.txt
django_urlconf_export-1.1.1.dist-info/RECORD
